dendrify/__init__.py
dendrify/_version.py
dendrify/cli.py
gitdendrify-0.2.0.dist-info/COPYING
gitdendrify-0.2.0.dist-info/COPYING~
gitdendrify-0.2.0.dist-info/LICENCE.txt
gitdendrify-0.2.0.dist-info/METADATA
gitdendrify-0.2.0.dist-info/WHEEL
gitdendrify-0.2.0.dist-info/entry_points.txt
gitdendrify-0.2.0.dist-info/top_level.txt
gitdendrify-0.2.0.dist-info/RECORD
