Metadata-Version: 2.1
Name: gitdendrify
Version: 0.2.0
Summary: Transform git history between linear and structured forms
Home-page: https://github.com/bennorth/git-dendrify
Author: Ben North
Author-email: ben@redfrontdoor.org
License: UNKNOWN
Platform: UNKNOWN
Classifier: Programming Language :: Python :: 3
Classifier: License :: OSI Approved :: GNU General Public License v3 or later (GPLv3+)
Classifier: Development Status :: 4 - Beta
Classifier: Operating System :: OS Independent
Classifier: Intended Audience :: Developers
Classifier: Intended Audience :: Education
Requires-Python: >=3.5
Requires-Dist: pygit2 (>=0.27.1)
Requires-Dist: docopt
